ibmvia_autoconf/__init__.py
ibmvia_autoconf/__main__.py
ibmvia_autoconf/access_control.py
ibmvia_autoconf/appliance.py
ibmvia_autoconf/configure.py
ibmvia_autoconf/container.py
ibmvia_autoconf/federation.py
ibmvia_autoconf/webseal.py
ibmvia_autoconf/util/__init__.py
ibmvia_autoconf/util/configure_util.py
ibmvia_autoconf/util/constants.py
ibmvia_autoconf/util/data_util.py
ibmvia_autoconf-0.3.13.dist-info/licenses/LICENCE.md
ibmvia_autoconf-0.3.13.dist-info/METADATA
ibmvia_autoconf-0.3.13.dist-info/WHEEL
ibmvia_autoconf-0.3.13.dist-info/top_level.txt
ibmvia_autoconf-0.3.13.dist-info/RECORD
