Metadata-Version: 2.4
Name: ibmvia_autoconf
Version: 0.3.13
Summary: YAML based configuration automation for IBM Verify Identity Access
Author: Lachlan Gleeson
Author-email: lgleeson@au1.ibm.com
License: Apache2.0
Project-URL: Homepage, https://github.com/lachlan-ibm/ibmvia_autoconf
Project-URL: Documentation, https://lachlan-ibm.github.io/ibmvia_autoconf
Project-URL: Source, https://github.com/lachlan-ibm/ibmvia_autoconf
Project-URL: Tracker, https://github.com/lachlan-ibm/ibmvia_autoconf/issues
Keywords: ivia,isva,isam,ibm verify,ibm verify identiy access,ibm security access manager,ibm security verify access
License-File: LICENCE.md
Requires-Dist: requests
Requires-Dist: PyYAML
Requires-Dist: pyivia
Requires-Dist: kubernetes
Requires-Dist: docker-compose
Requires-Dist: typing
Requires-Dist: pyyaml==5.4.1
Requires-Dist: Cython<3
Dynamic: author
Dynamic: author-email
Dynamic: description
Dynamic: description-content-type
Dynamic: keywords
Dynamic: license
Dynamic: license-file
Dynamic: project-url
Dynamic: requires-dist
Dynamic: summary
